{
 "cwbopendata": {
  "@xmlns": "urn:cwb:gov:tw:cwbcommon:0.1", 
  "identifier": "e225e5ee-0263-11e9-9e29-d89d67177004", 
  "sender": "weather@cwb.gov.tw", 
  "sent": "2018-12-18T09:26:03+08:00", 
  "status": "Actual", 
  "msgType": "Issue", 
  "scope": "Public", 
  "dataid": "B0072-002", 
  "dataset": {
   "datasetinfo": {
    "datasetDescription": "地理資訊", 
    "parameterset": [
     {
      "parameterName": "經度範圍", 
      "parameterValue": "117.55 - 123.92"
     }, 
     {
      "parameterName": "緯度範圍", 
      "parameterValue": "20.79 - 26.66"
     }
    ]
   }, 
   "time": {
    "obsTime": "2018-12-18T09:00:00+08:00"
   }, 
   "resource": {
    "resourceDesc": "月氣溫面化圖", 
    "mimeType": "image/png", 
    "uri": "https://opendata.cwb.gov.tw/fileapi/opendata/DIV3/C-B0072-002.zip"
   }
  }
 }
}